motion_lake_client/__init__.py
motion_lake_client/client.py
motion_lake_client-0.0.15.dist-info/LICENSE
motion_lake_client-0.0.15.dist-info/METADATA
motion_lake_client-0.0.15.dist-info/WHEEL
motion_lake_client-0.0.15.dist-info/top_level.txt
motion_lake_client-0.0.15.dist-info/RECORD
