Metadata-Version: 2.1
Name: motion-lake-client
Version: 0.0.15
Summary: Motion Lake Client, a client for the Motion Lake API (a Mobility Data Lake)
Author-email: Gaspard Merten <gaspard.mp.work@gmail.com>
License: All Rights Reserved
Project-URL: Homepage, https://github.com/GaspardMerten/motion-lake-client
Keywords: motion-lake,mobility,data,api,client
Classifier: License :: Other/Proprietary License
Classifier: Programming Language :: Python
Classifier: Programming Language :: Python :: 3
Requires-Python: >=3.9
License-File: LICENSE
Requires-Dist: requests
